[{"id": "f1pt6tro", "detected": false}, {"id": "f1qrf87h", "detected": false}, {"id": "f1uf3g86", "detected": false}, {"id": "f1vvwusx", "detected": false}, {"id": "f24hyg1h", "detected": false}, {"id": "f29u8uri", "detected": false}, {"id": "f2k5c3z6", "detected": false}, {"id": "f309hsuw", "detected": false}, {"id": "f33dnreh", "detected": false}, {"id": "f37cqrwq", "detected": false}, {"id": "f37l5rpt", "detected": false}, {"id": "f3ikn9nt", "detected": false}, {"id": "f3ob9v1t", "detected": false}, {"id": "f3u1y90b", "detected": false}, {"id": "f3uz3aoe", "detected": false}, {"id": "f4akdnad", "detected": false}, {"id": "f4fxen3m", "detected": false}, {"id": "f4ln5rgs", "detected": false}, {"id": "f4nzkrsn", "detected": false}, {"id": "f4ofpatm", "detected": false}, {"id": "f4t8ma10", "detected": false}, {"id": "f4zkrway", "detected": false}, {"id": "f4zzw5uk", "detected": false}, {"id": "f51z58b4", "detected": false}, {"id": "f57vh2d3", "detected": false}, {"id": "f5nk4otb", "detected": false}, {"id": "f5tkkk5n", "detected": false}, {"id": "f613tazs", "detected": false}, {"id": "f66vd7wb", "detected": false}, {"id": "f6fu547o", "detected": false}, {"id": "f6gk4p9o", "detected": false}, {"id": "f6nv5xu6", "detected": true}, {"id": "f6nxxx5f", "detected": false}, {"id": "f6y5v9jr", "detected": false}, {"id": "f7fbz753", "detected": false}, {"id": "f7ietcps", "detected": false}, {"id": "f7k5mtvg", "detected": false}, {"id": "f7mvq356", "detected": false}, {"id": "f7tbx3th", "detected": false}, {"id": "f80piqvi", "detected": false}, {"id": "f81bgksd", "detected": false}, {"id": "f8awstyb", "detected": false}, {"id": "f8hstrlt", "detected": false}, {"id": "f8r1pc6k", "detected": false}, {"id": "f91gdr95", "detected": false}, {"id": "f973p1dj", "detected": false}, {"id": "f9cfwawq", "detected": false}, {"id": "f9t6gxny", "detected": false}, {"id": "f9to0wzn", "detected": false}, {"id": "fa32j5uf", "detected": false}, {"id": "fa5qub00", "detected": false}, {"id": "fa6xkz2d", "detected": false}, {"id": "fa8014eh", "detected": false}, {"id": "fao72kz0", "detected": false}, {"id": "faq6vzna", "detected": false}, {"id": "fazw2fb7", "detected": false}, {"id": "fb0lj3qa", "detected": false}, {"id": "fb6qdfe2", "detected": false}, {"id": "fbovb1zj", "detected": false}, {"id": "fbwp3u53", "detected": false}, {"id": "fc1k8j0k", "detected": false}, {"id": "fc5z5l9h", "detected": false}, {"id": "fcbshut9", "detected": false}, {"id": "fchao73k", "detected": false}, {"id": "fcopzfzz", "detected": false}, {"id": "fcqml8qq", "detected": false}, {"id": "fcuzlzoo", "detected": false}, {"id": "fdib0sxg", "detected": false}, {"id": "fdjh1y3m", "detected": false}, {"id": "fdssxovb", "detected": false}, {"id": "fdtnbs5x", "detected": false}, {"id": "fdx89i8y", "detected": false}, {"id": "fdxk31wb", "detected": false}, {"id": "fdzwpwsd", "detected": false}, {"id": "fe5opli4", "detected": false}, {"id": "fesvjlv8", "detected": false}, {"id": "feyuhz1g", "detected": false}, {"id": "fezac2ex", "detected": false}, {"id": "ff2wcfie", "detected": false}, {"id": "ff4ng4tf", "detected": false}, {"id": "ffaht4a2", "detected": false}, {"id": "ffcvedqf", "detected": false}, {"id": "fflncc2a", "detected": true}, {"id": "ffsaifau", "detected": false}, {"id": "ffvmam3j", "detected": false}, {"id": "fg0djq1p", "detected": false}, {"id": "fggw1jyk", "detected": false}, {"id": "fghpas0z", "detected": false}, {"id": "fgkvtr43", "detected": false}, {"id": "fgyw6zbn", "detected": false}, {"id": "fh024kwk", "detected": false}, {"id": "fh22cp4o", "detected": false}, {"id": "fh9194b7", "detected": false}, {"id": "fhcc1p7x", "detected": false}, {"id": "fheyzqqx", "detected": false}, {"id": "fhoe3mxz", "detected": false}, {"id": "fhs2qjed", "detected": false}, {"id": "fhzla6ov", "detected": false}, {"id": "fi53llp0", "detected": false}, {"id": "filkjxjq", "detected": false}, {"id": "fimtb6t9", "detected": false}, {"id": "fitpf7zm", "detected": false}, {"id": "fj1pinix", "detected": false}, {"id": "fjid8y68", "detected": false}, {"id": "fk2k0jj4", "detected": false}, {"id": "fk6o81yr", "detected": false}, {"id": "fk8ulidi", "detected": false}, {"id": "fknwbhkv", "detected": false}, {"id": "fkyof4rp", "detected": false}, {"id": "fl0463na", "detected": false}, {"id": "fl79r9kp", "detected": false}, {"id": "fl7q15wh", "detected": false}, {"id": "fl9mq11p", "detected": false}, {"id": "flvrktgu", "detected": false}, {"id": "flvywapk", "detected": false}, {"id": "fmcie4ac", "detected": false}, {"id": "fml00ml2", "detected": false}, {"id": "fmr5ll1d", "detected": false}, {"id": "fmw4v1fj", "detected": false}, {"id": "fmw4vchr", "detected": false}, {"id": "fmykith4", "detected": false}, {"id": "fn5n6rve", "detected": false}, {"id": "fnf8t9ml", "detected": false}, {"id": "fngbg4pd", "detected": false}, {"id": "fnscqqav", "detected": false}, {"id": "fo30po3j", "detected": false}, {"id": "fogevokq", "detected": false}, {"id": "foj237b7", "detected": false}, {"id": "fom3vqri", "detected": false}, {"id": "fonn13fh", "detected": false}, {"id": "foqsr41s", "detected": false}, {"id": "fotp3z4r", "detected": false}, {"id": "fozlaf7z", "detected": false}, {"id": "fozz1jpa", "detected": false}, {"id": "fp1k8rzu", "detected": false}, {"id": "fph1kt03", "detected": false}, {"id": "fpkp555n", "detected": false}, {"id": "fpqeqqr7", "detected": false}, {"id": "fq12pqqx", "detected": false}, {"id": "fqajgojc", "detected": false}, {"id": "fqebiwrc", "detected": false}, {"id": "fqgdm1iy", "detected": false}, {"id": "fqgmqqfw", "detected": false}, {"id": "fqi1hf2y", "detected": false}, {"id": "fqmpzx56", "detected": false}, {"id": "fqnbia9r", "detected": false}, {"id": "fqod1yoz", "detected": false}, {"id": "fqtg7hzl", "detected": false}, {"id": "fqtndy69", "detected": false}, {"id": "fr3pqpo3", "detected": false}, {"id": "fr6mqw76", "detected": false}, {"id": "frl3hs0i", "detected": false}, {"id": "frv1l6ck", "detected": false}, {"id": "fs7i19mo", "detected": false}, {"id": "fs87veue", "detected": false}, {"id": "fsmhn5o4", "detected": false}, {"id": "fsumuxqj", "detected": false}, {"id": "fsv871yz", "detected": false}, {"id": "ft1pwvz0", "detected": false}, {"id": "ft3cbz2d", "detected": false}, {"id": "ftixdwr0", "detected": false}, {"id": "ftmttqlg", "detected": false}, {"id": "ftwr2z0a", "detected": false}, {"id": "fu20vmak", "detected": false}, {"id": "fu3cegsa", "detected": false}, {"id": "fu547otb", "detected": false}, {"id": "fulz2ads", "detected": false}, {"id": "fux1ss1j", "detected": false}, {"id": "fuyc5atd", "detected": false}, {"id": "fv7pivpa", "detected": false}, {"id": "fv9xomig", "detected": false}, {"id": "fvjnhav0", "detected": false}, {"id": "fvpig3yv", "detected": false}, {"id": "fvtacblq", "detected": false}, {"id": "fvtm6x4k", "detected": false}, {"id": "fw0c20x4", "detected": false}, {"id": "fw79gqqq", "detected": false}, {"id": "fwb5hsts", "detected": false}, {"id": "fwg895na", "detected": false}, {"id": "fwp5wlf0", "detected": false}, {"id": "fwtevtx3", "detected": false}, {"id": "fx0r99lc", "detected": false}, {"id": "fx3b4e0b", "detected": false}, {"id": "fxa2wd77", "detected": false}, {"id": "fxcbbcmm", "detected": false}, {"id": "fxgnb3ep", "detected": false}, {"id": "fxhn5a5w", "detected": false}, {"id": "fxqp6xgh", "detected": false}, {"id": "fxuj5ogq", "detected": false}, {"id": "fyv6wxmt", "detected": false}, {"id": "fz2rimc6", "detected": false}, {"id": "fz7uys9w", "detected": false}, {"id": "fzdtc5pa", "detected": false}, {"id": "fzdy5ddp", "detected": false}, {"id": "fzny2j6w", "detected": false}, {"id": "fzq1w09y", "detected": true}, {"id": "fzrwmh05", "detected": false}, {"id": "fztos6gk", "detected": false}, {"id": "g07g0iij", "detected": false}, {"id": "g08e077u", "detected": false}, {"id": "g0k1irbs", "detected": false}, {"id": "g0n3pi6w", "detected": false}, {"id": "g0u43qlx", "detected": false}, {"id": "g11sxxrp", "detected": false}, {"id": "g160wr0m", "detected": false}, {"id": "g1m69p2v", "detected": false}, {"id": "g1mdeymh", "detected": false}, {"id": "g1r1cqki", "detected": false}, {"id": "g1so1esp", "detected": false}, {"id": "g2imi74b", "detected": false}, {"id": "g2krt47z", "detected": false}, {"id": "g2o4sauf", "detected": false}, {"id": "g2tlsy8i", "detected": false}, {"id": "g2txa7bh", "detected": false}, {"id": "g38rajib", "detected": false}, {"id": "g39bd2ee", "detected": false}, {"id": "g3dcmyxb", "detected": false}, {"id": "g3fye4hq", "detected": false}, {"id": "g3hkcqwb", "detected": false}, {"id": "g3jbrrd4", "detected": false}, {"id": "g3yn2yjw", "detected": false}, {"id": "g4asmzx4", "detected": false}, {"id": "g4kf3z16", "detected": false}, {"id": "g5ascc4d", "detected": false}, {"id": "g5rifwr0", "detected": false}, {"id": "g5x1rtwf", "detected": false}, {"id": "g5xtwhxx", "detected": false}, {"id": "g680iuga", "detected": false}, {"id": "g6a8mlik", "detected": false}, {"id": "g6q62rxy", "detected": false}, {"id": "g6yl58ap", "detected": false}, {"id": "g727nk81", "detected": false}, {"id": "g739zobz", "detected": false}, {"id": "g7f9fzja", "detected": false}, {"id": "g7g2mvkg", "detected": false}, {"id": "g7h0qmg0", "detected": false}, {"id": "g7nfdinu", "detected": false}, {"id": "g7qsodmx", "detected": false}, {"id": "g7t0lshg", "detected": false}, {"id": "g89vb92g", "detected": false}, {"id": "g8ap02xg", "detected": false}, {"id": "g8f9prnn", "detected": false}, {"id": "g8ibhbhu", "detected": false}, {"id": "g9e07pme", "detected": false}, {"id": "g9ei2lim", "detected": false}, {"id": "g9h8lyk0", "detected": false}, {"id": "g9o9ih4o", "detected": true}, {"id": "g9slxk01", "detected": false}, {"id": "ga0xmvru", "detected": false}, {"id": "ga9ta76n", "detected": false}, {"id": "gabh7rrz", "detected": false}, {"id": "gaghft9z", "detected": false}, {"id": "gb205hu0", "detected": false}, {"id": "gb8iy525", "detected": false}, {"id": "gba9in2x", "detected": false}, {"id": "gbhlft2n", "detected": false}, {"id": "gbiaf92m", "detected": false}, {"id": "gbj72btq", "detected": false}, {"id": "gbrg4q9w", "detected": false}, {"id": "gchyb7th", "detected": false}, {"id": "gcp3hyw7", "detected": false}, {"id": "gd40cm0t", "detected": false}, {"id": "gd5yshgp", "detected": false}, {"id": "gd9ds7a0", "detected": false}, {"id": "gdgk8dzv", "detected": false}, {"id": "gdgy87qt", "detected": false}, {"id": "gdofmaok", "detected": false}, {"id": "gdpuh4gb", "detected": false}, {"id": "gdpxtpjb", "detected": false}, {"id": "ge3ai6ay", "detected": false}, {"id": "ge9ny3mu", "detected": false}, {"id": "geejgbjx", "detected": false}, {"id": "gejfoxm3", "detected": false}, {"id": "gexas2r8", "detected": false}, {"id": "geyv6nh4", "detected": false}, {"id": "gf9fdnvr", "detected": false}, {"id": "gfe0b17m", "detected": false}, {"id": "gfp94k3a", "detected": false}, {"id": "gfr16wu1", "detected": false}, {"id": "gfvm3kfz", "detected": false}, {"id": "gfvnnvbz", "detected": false}, {"id": "ggacsqnb", "detected": false}, {"id": "ggo9dvws", "detected": false}, {"id": "ggxp5cit", "detected": false}, {"id": "gh02wpkq", "detected": false}, {"id": "gh2ij4tt", "detected": false}, {"id": "gh6h7l8q", "detected": false}, {"id": "gh9zcoyw", "detected": false}, {"id": "ghbtmpt1", "detected": false}, {"id": "ghdiluvn", "detected": false}, {"id": "ghf3obs0", "detected": false}, {"id": "ghiy1bfw", "detected": false}, {"id": "ghm56vu6", "detected": true}, {"id": "ghy2dxm4", "detected": false}, {"id": "gi4meiad", "detected": false}, {"id": "gicr6d86", "detected": false}, {"id": "giorfzcp", "detected": false}, {"id": "giunwela", "detected": false}, {"id": "gj3ey82p", "detected": false}, {"id": "gj7nrsko", "detected": false}, {"id": "gjfbnug3", "detected": false}, {"id": "gjuzxged", "detected": false}, {"id": "gk82p5yr", "detected": false}, {"id": "gk8mydl0", "detected": false}, {"id": "gkg5khl1", "detected": false}, {"id": "gktuf15n", "detected": false}, {"id": "gkzjrumx", "detected": false}, {"id": "gl7jy7ot", "detected": false}, {"id": "glckwt2e", "detected": false}, {"id": "glg08yvu", "detected": false}, {"id": "glqkbec5", "detected": false}, {"id": "gm2t5woq", "detected": false}, {"id": "gminudc3", "detected": false}, {"id": "gmmtfhsf", "detected": false}, {"id": "gmq2p014", "detected": false}, {"id": "gmrzzqo1", "detected": false}, {"id": "gmtvppfn", "detected": false}, {"id": "gnzclmcb", "detected": false}, {"id": "go8utd9j", "detected": false}, {"id": "go9pv7q4", "detected": false}, {"id": "godlught", "detected": false}, {"id": "goe2prj7", "detected": false}, {"id": "goefqbki", "detected": false}, {"id": "gohmprsh", "detected": false}, {"id": "gom6736z", "detected": false}, {"id": "gomqxmqo", "detected": false}, {"id": "got73aws", "detected": false}, {"id": "goxaiqus", "detected": false}, {"id": "gpagi3xa", "detected": false}, {"id": "gq2uokff", "detected": false}, {"id": "gq34pggc", "detected": false}, {"id": "gqcqnyia", "detected": false}, {"id": "gqk820ps", "detected": false}, {"id": "gqllx70r", "detected": false}, {"id": "gqt3l8or", "detected": false}, {"id": "gqymh33d", "detected": false}, {"id": "gr7omj8b", "detected": false}, {"id": "graejpfa", "detected": false}, {"id": "grc38p58", "detected": false}, {"id": "groabeaw", "detected": false}, {"id": "grp2u4dt", "detected": false}, {"id": "grrrixci", "detected": false}, {"id": "gs59ymzy", "detected": false}, {"id": "gsem2fit", "detected": false}, {"id": "gsm7rbrx", "detected": false}, {"id": "gss8k5ij", "detected": false}, {"id": "gt5nza9s", "detected": false}, {"id": "gt8j3ao8", "detected": false}, {"id": "gtg5haxq", "detected": false}, {"id": "gu1tlxzb", "detected": false}, {"id": "gu5io8ve", "detected": false}, {"id": "gu8nqpck", "detected": false}, {"id": "gueifo28", "detected": false}, {"id": "gujz3ywz", "detected": false}, {"id": "guktq5sm", "detected": false}, {"id": "gup30l1r", "detected": false}, {"id": "gurt1rwv", "detected": false}, {"id": "guuw0580", "detected": false}, {"id": "gv812hnc", "detected": false}, {"id": "gveh6o7y", "detected": false}, {"id": "gvt67k37", "detected": false}, {"id": "gvyie6iv", "detected": false}, {"id": "gwdfo1nn", "detected": false}, {"id": "gxekbzcm", "detected": false}, {"id": "gxl9ysu5", "detected": false}, {"id": "gy8buxin", "detected": false}, {"id": "gyd7gcid", "detected": false}, {"id": "gynioloa", "detected": false}, {"id": "gyr58mx4", "detected": false}, {"id": "gz0xzijs", "detected": false}, {"id": "gz2ueaxy", "detected": false}, {"id": "gzcw6j7o", "detected": false}, {"id": "gzw6iz12", "detected": false}, {"id": "h0squs4m", "detected": false}, {"id": "h0z1euwe", "detected": false}, {"id": "h12pgx40", "detected": false}, {"id": "h168287s", "detected": false}, {"id": "h19yx6yi", "detected": false}, {"id": "h1i8yaty", "detected": false}, {"id": "h1m3jlzo", "detected": false}, {"id": "h1myl54n", "detected": false}, {"id": "h1sij57n", "detected": false}, {"id": "h1sixv96", "detected": false}, {"id": "h1tbgkos", "detected": false}, {"id": "h1xawj28", "detected": false}, {"id": "h1xjg2y8", "detected": false}, {"id": "h1z97ytx", "detected": false}, {"id": "h22be4n2", "detected": false}, {"id": "h25zhl0q", "detected": false}, {"id": "h2bvwv6y", "detected": false}, {"id": "h2csanha", "detected": false}, {"id": "h2nxxms3", "detected": false}, {"id": "h2r9pegl", "detected": false}, {"id": "h2tn8b8z", "detected": false}, {"id": "h2udx1zf", "detected": false}, {"id": "h33hw8d0", "detected": false}, {"id": "h380nqpt", "detected": false}, {"id": "h3pfi14k", "detected": false}, {"id": "h3wqa1vr", "detected": false}, {"id": "h3z3de4e", "detected": false}, {"id": "h4ejshk0", "detected": false}, {"id": "h4pzngvx", "detected": false}, {"id": "h4wlxa85", "detected": false}, {"id": "h4ynh2e8", "detected": false}, {"id": "h548jrpe", "detected": false}, {"id": "h5eglkxg", "detected": false}, {"id": "h6m3sgur", "detected": false}, {"id": "h6oq7qh9", "detected": true}, {"id": "h6yyczqp", "detected": false}, {"id": "h742dy3x", "detected": false}, {"id": "h74kudyz", "detected": false}, {"id": "h7psxmdx", "detected": false}, {"id": "h7redy0v", "detected": false}, {"id": "h7u0s3kd", "detected": false}, {"id": "h80jwzgo", "detected": false}, {"id": "h8xu63th", "detected": false}, {"id": "h9dup5bm", "detected": false}, {"id": "h9vgky5c", "detected": false}, {"id": "hamsxaaq", "detected": false}, {"id": "hapm4yqz", "detected": false}, {"id": "harji6yb", "detected": false}, {"id": "hba5mf36", "detected": false}, {"id": "hbblbqk2", "detected": false}, {"id": "hbxxhtd2", "detected": false}, {"id": "hcaf0cor", "detected": false}, {"id": "hcclxntx", "detected": false}, {"id": "hce0lo1z", "detected": false}, {"id": "hcg7fd14", "detected": false}, {"id": "hcgw33a8", "detected": false}, {"id": "hdczp0nw", "detected": false}, {"id": "hdgokmvl", "detected": false}, {"id": "hdiy4nrm", "detected": false}, {"id": "hdm6k6hg", "detected": false}, {"id": "hdo61xn8", "detected": false}, {"id": "hdszw1ye", "detected": false}, {"id": "hdx1bjt4", "detected": false}, {"id": "he17o7pn", "detected": false}, {"id": "he2a8q0o", "detected": false}, {"id": "heddyy83", "detected": false}, {"id": "herpe5o8", "detected": false}, {"id": "hesxigzq", "detected": false}, {"id": "hexw8l85", "detected": false}, {"id": "hezul4ae", "detected": false}, {"id": "hf4luf31", "detected": false}, {"id": "hfrrcv1e", "detected": false}, {"id": "hg3hh0xi", "detected": false}, {"id": "hg9ozgxl", "detected": false}, {"id": "hgrp1cca", "detected": false}, {"id": "hgygmjvb", "detected": false}, {"id": "hha1pjgf", "detected": false}, {"id": "hhwmf1gz", "detected": false}, {"id": "hhzlyraq", "detected": false}, {"id": "hif5sl1y", "detected": false}, {"id": "hifk0vzy", "detected": false}, {"id": "hiy5rv1a", "detected": false}, {"id": "hizebg9k", "detected": false}, {"id": "hj071v7w", "detected": false}, {"id": "hj755nf4", "detected": false}, {"id": "hjc5ysa4", "detected": false}, {"id": "hjcwlcks", "detected": false}, {"id": "hjkwbjpc", "detected": false}, {"id": "hjsos58y", "detected": false}, {"id": "hk6hmrti", "detected": false}, {"id": "hkd6k7rm", "detected": false}, {"id": "hkkldixs", "detected": false}, {"id": "hkz2u2tn", "detected": false}, {"id": "hl5thlvj", "detected": false}, {"id": "hlbprfeg", "detected": false}, {"id": "hlszm6vd", "detected": false}, {"id": "hlu2zlgl", "detected": false}, {"id": "hm63q68j", "detected": false}, {"id": "hmd6z3a8", "detected": false}, {"id": "hmezvsq3", "detected": false}, {"id": "hnbt3v23", "detected": false}, {"id": "hnck5qda", "detected": false}, {"id": "hnf877vr", "detected": false}, {"id": "hnmoqdp3", "detected": false}, {"id": "hnpvcub7", "detected": false}, {"id": "hny2n5tn", "detected": false}, {"id": "ho3xjvoe", "detected": false}, {"id": "ho9cy9pe", "detected": false}, {"id": "hoabed5r", "detected": false}, {"id": "hopq0ux5", "detected": false}, {"id": "hoq5e7l7", "detected": false}, {"id": "hp2rnzbc", "detected": false}, {"id": "hp60iq7s", "detected": false}, {"id": "hp899df5", "detected": false}, {"id": "hpitza7u", "detected": false}, {"id": "hpkji6nr", "detected": false}, {"id": "hppipg6a", "detected": false}, {"id": "hpvidqh7", "detected": false}, {"id": "hq4hoawq", "detected": false}, {"id": "hqwp8xfa", "detected": false}, {"id": "hrav8588", "detected": false}, {"id": "hrkmrfsf", "detected": false}, {"id": "hrliagp3", "detected": false}, {"id": "hrqzdua4", "detected": false}, {"id": "hrri01x5", "detected": false}, {"id": "hruu5e51", "detected": false}, {"id": "hrx7bnzt", "detected": false}, {"id": "hs21hd4y", "detected": false}, {"id": "hs4dilrz", "detected": false}, {"id": "hs7auigj", "detected": false}, {"id": "hsa7hez7", "detected": false}, {"id": "hsao2qwk", "detected": false}, {"id": "hsbdj532", "detected": false}, {"id": "hsg04ajm", "detected": false}, {"id": "hsh1grg9", "detected": false}, {"id": "hsm6agus", "detected": false}, {"id": "hsxpzlc8", "detected": false}, {"id": "ht2ibtrv", "detected": false}, {"id": "htfnsgpy", "detected": false}, {"id": "hu2m6nwm", "detected": false}, {"id": "hu97ng0a", "detected": false}, {"id": "huaahl0f", "detected": false}, {"id": "hul0opxn", "detected": false}, {"id": "hv0ehlit", "detected": false}, {"id": "hv1f070v", "detected": false}, {"id": "hv1nm3v1", "detected": false}, {"id": "hvdq0mjk", "detected": false}, {"id": "hvgnqgmj", "detected": false}, {"id": "hvr04jcr", "detected": false}, {"id": "hvraemy8", "detected": false}, {"id": "hvy3nuko", "detected": false}, {"id": "hvymq1a3", "detected": false}, {"id": "hw0bupmt", "detected": false}, {"id": "hwbbmfsf", "detected": false}, {"id": "hwekqdvn", "detected": false}, {"id": "hwikvnzz", "detected": false}, {"id": "hwm518zr", "detected": false}, {"id": "hwtek17m", "detected": false}, {"id": "hwy8fvpt", "detected": false}, {"id": "hx0l7ror", "detected": false}, {"id": "hxa7hy7a", "detected": false}, {"id": "hxiziyzj", "detected": false}, {"id": "hxr4g0cy", "detected": false}, {"id": "hy1hnxiy", "detected": false}, {"id": "hya0eiva", "detected": false}, {"id": "hycx8ae0", "detected": false}, {"id": "hylu6k7p", "detected": false}, {"id": "hyou7x5y", "detected": false}, {"id": "hyvezrad", "detected": false}, {"id": "hyycqa3s", "detected": false}, {"id": "hyz1ov5v", "detected": false}, {"id": "hztay12y", "detected": false}, {"id": "i064vj2m", "detected": false}, {"id": "i08wojp2", "detected": false}, {"id": "i15cqzcu", "detected": false}, {"id": "i174lxz1", "detected": false}, {"id": "i1endp1e", "detected": false}, {"id": "i1jlmflu", "detected": false}, {"id": "i1n6clpd", "detected": false}, {"id": "i1niskyw", "detected": false}, {"id": "i1nq0ei0", "detected": false}]